{
  "apiVersion": 2,
  "name": "snow-monkey-blocks/section",
	"title": "Section",
	"description": "Contents can be separated by appropriate margins.",
  "category": "smb-section",
  "attributes": {
    "wrapperTagName": {
      "type": "string",
      "default": "div"
    },
    "titleTagName": {
      "type": "string",
      "default": "h2"
    },
    "title": {
      "type": "string",
      "source": "html",
      "selector": ".smb-section__title",
      "default": ""
    },
    "subtitle": {
      "type": "string",
      "source": "html",
      "selector": ".smb-section__subtitle",
      "default": ""
    },
    "lede": {
      "type": "string",
      "source": "html",
      "selector": ".smb-section__lede",
      "default": ""
    },
    "backgroundHorizontalPosition": {
      "type": "number",
      "default": 0
    },
    "backgroundVerticalPosition": {
      "type": "number",
      "default": 0
    },
    "isBackgroundNoOver": {
      "type": "boolean",
      "default": false
    },
    "backgroundColor": {
      "type": "string"
    },
    "backgroundGradientColor": {
      "type": "string"
    },
    "backgroundTexture": {
      "type": "string"
    },
    "backgroundTextureOpacity": {
      "type": "number",
      "default": 1
    },
    "fixedBackgroundColor": {
      "type": "string"
    },
    "fixedBackgroundGradientColor": {
      "type": "string"
    },
    "fixedBackgroundTexture": {
      "type": "string"
    },
    "fixedBackgroundTextureOpacity": {
      "type": "number",
      "default": 1
    },
    "textColor": {
      "type": "string"
    },
    "contentsWidth": {
      "type": "string",
      "default": null
    },
    "isSlim": {
      "type": "boolean",
      "default": false
    },
    "topDividerType": {
      "type": "string",
      "default": "tilt"
    },
    "topDividerLevel": {
      "type": "number",
      "default": 0
    },
    "topDividerColor": {
      "type": "string",
      "default": "#fff"
    },
    "topDividerVerticalPosition": {
      "type": "number",
      "default": 0
    },
    "bottomDividerType": {
      "type": "string",
      "default": "tilt"
    },
    "bottomDividerLevel": {
      "type": "number",
      "default": 0
    },
    "bottomDividerColor": {
      "type": "string",
      "default": "#fff"
    },
    "bottomDividerVerticalPosition": {
      "type": "number",
      "default": 0
    },
    "height": {
      "type": "string",
      "default": "fit"
    },
    "contentsAlignment": {
      "type": "string",
      "default": ""
    }
  },
  "supports": {
    "align": [ "wide", "full" ],
    "anchor": true
  },
  "example": {
  	"attributes": {
      "title": "Lorem ipsum dolor sit amet"
    },
    "innerBlocks": [
      {
        "name": "core/paragraph",
        "attributes": {
          "content": "Lorem ipsum dolor sit amet, consectetur adipiscing elit, sed do eiusmod tempor incididunt ut labore et dolore magna aliqua. Ut enim ad minim veniam"
        }
      }
    ]
  }
}
